_dlib_pybind11.cpython-313-x86_64-linux-gnu.so
dlib/__init__.py
dlib_bin-20.0.0.dist-info/METADATA
dlib_bin-20.0.0.dist-info/WHEEL
dlib_bin-20.0.0.dist-info/top_level.txt
dlib_bin-20.0.0.dist-info/RECORD
dlib_bin-20.0.0.dist-info/licenses/LICENSE.txt
